smoothopt/__init__.py
smoothopt/api.py
smoothopt/optimization.py
smoothopt/types.py
smoothopt-0.1.0.dist-info/METADATA
smoothopt-0.1.0.dist-info/WHEEL
smoothopt-0.1.0.dist-info/RECORD
