Metadata-Version: 2.4
Name: smoothopt
Version: 0.1.0
Summary: Add your description here
Requires-Python: >=3.13
Requires-Dist: botorch>=0.14.0
Requires-Dist: dill>=0.3.0
Requires-Dist: rich>=14.0.0
